naanthan_da_leo/__init__.py
naanthan_da_leo/leo.py
naanthan_da_leo-1.1.dist-info/LICENSE.txt
naanthan_da_leo-1.1.dist-info/METADATA
naanthan_da_leo-1.1.dist-info/WHEEL
naanthan_da_leo-1.1.dist-info/top_level.txt
naanthan_da_leo-1.1.dist-info/RECORD
