Metadata-Version: 2.1
Name: naanthan-da-leo
Version: 1.1
Summary: streamlit custome css function
Home-page: UNKNOWN
Author: leo joel roys
Author-email: joelroys637@gmail.com
License: MIT
Project-URL: Source Repository, https://github.com/Joelroys637
Platform: UNKNOWN
Requires-Dist: streamlit
